ctrl/__init__.py
ctrl/commons/__init__.py
ctrl/commons/tree.py
ctrl/commons/utils.py
ctrl/concepts/__init__.py
ctrl/concepts/concept.py
ctrl/concepts/concept_tree.py
ctrl/instances/DTD.py
ctrl/instances/__init__.py
ctrl/instances/image_dataset_tree.py
ctrl/instances/md_tree.py
ctrl/instances/taxonomies.py
ctrl/strategies/__init__.py
ctrl/strategies/attributes_strategy.py
ctrl/strategies/data_strategy.py
ctrl/strategies/incremental_strategy.py
ctrl/strategies/input_domain_strategy.py
ctrl/strategies/label_permutation_strategy.py
ctrl/strategies/mixed_strategy.py
ctrl/strategies/random_mutation_strategy.py
ctrl/strategies/split_strategy.py
ctrl/strategies/task_creation_strategy.py
ctrl/streams/__init__.py
ctrl/streams/default_datasets.yaml
ctrl/streams/s_in.yaml
ctrl/streams/s_long.yaml
ctrl/streams/s_minus.yaml
ctrl/streams/s_out.yaml
ctrl/streams/s_pl.yaml
ctrl/streams/s_plus.yaml
ctrl/tasks/__init__.py
ctrl/tasks/task.py
ctrl/tasks/task_generator.py
ctrl/transformations/__init__.py
ctrl/transformations/identity_transformation.py
ctrl/transformations/img_rotations.py
ctrl/transformations/noisy_nn_transformation.py
ctrl/transformations/rainbow_transformation.py
ctrl/transformations/randperm_transformation.py
ctrl/transformations/transformation.py
ctrl/transformations/transformation_pool.py
ctrl/transformations/transformation_tree.py
ctrl/transformations/utils.py
tests/__init__.py
tests/test_ctrl.py
ctrl_bench-0.0.3.dist-info/LICENSE
ctrl_bench-0.0.3.dist-info/METADATA
ctrl_bench-0.0.3.dist-info/WHEEL
ctrl_bench-0.0.3.dist-info/top_level.txt
ctrl_bench-0.0.3.dist-info/RECORD
